odoo/addons/sale_order_warn_message/README.rst
odoo/addons/sale_order_warn_message/__init__.py
odoo/addons/sale_order_warn_message/__manifest__.py
odoo/addons/sale_order_warn_message/i18n/es.po
odoo/addons/sale_order_warn_message/i18n/it.po
odoo/addons/sale_order_warn_message/i18n/sale_order_warn_message.pot
odoo/addons/sale_order_warn_message/models/__init__.py
odoo/addons/sale_order_warn_message/models/sale_order.py
odoo/addons/sale_order_warn_message/readme/CONTRIBUTORS.md
odoo/addons/sale_order_warn_message/readme/DESCRIPTION.md
odoo/addons/sale_order_warn_message/static/description/icon.png
odoo/addons/sale_order_warn_message/static/description/index.html
odoo/addons/sale_order_warn_message/tests/__init__.py
odoo/addons/sale_order_warn_message/tests/test_sale_order_warn_message.py
odoo/addons/sale_order_warn_message/views/sale_order.xml
odoo_addon_sale_order_warn_message-18.0.1.0.1.dist-info/METADATA
odoo_addon_sale_order_warn_message-18.0.1.0.1.dist-info/WHEEL
odoo_addon_sale_order_warn_message-18.0.1.0.1.dist-info/top_level.txt
odoo_addon_sale_order_warn_message-18.0.1.0.1.dist-info/RECORD
